rnlp/__init__.py
rnlp/__main__.py
rnlp/_meta.py
rnlp/corpus.py
rnlp/parse.py
rnlp/textprocessing.py
rnlp/tests/__init__.py
rnlp/tests/tests.py
rnlp/tests/rnlptests/__init__.py
rnlp/tests/rnlptests/test_converter.py
rnlp/tests/rnlptests/test_parse.py
rnlp/tests/rnlptests/test_textprocessing.py
rnlp-0.3.2.dist-info/LICENSE
rnlp-0.3.2.dist-info/METADATA
rnlp-0.3.2.dist-info/WHEEL
rnlp-0.3.2.dist-info/top_level.txt
rnlp-0.3.2.dist-info/RECORD
