Metadata-Version: 2.1
Name: rnlp
Version: 0.3.2
Summary: Converts text corpora into a set of relational facts.
Home-page: https://github.com/hayesall/rnlp
Author: Alexander L. Hayes (@hayesall)
Author-email: hayesall@iu.edu
License: GPL-v3
Project-URL: Source, https://github.com/hayesall/rnlp
Project-URL: Tracker, https://github.com/hayesall/rnlp/issues
Keywords: nlp
Platform: UNKNOWN
Classifier: Development Status :: 4 - Beta
Classifier: License :: OSI Approved :: GNU General Public License v3 (GPLv3)
Classifier: Intended Audience :: Science/Research
Classifier: Operating System :: POSIX :: Linux
Classifier: Operating System :: Microsoft :: Windows :: Windows 10
Classifier: Programming Language :: Python :: 3.4
Classifier: Programming Language :: Python :: 3.5
Classifier: Programming Language :: Python :: 3.6
Classifier: Programming Language :: Python :: 3.7
Requires-Dist: nltk
Requires-Dist: tqdm
Requires-Dist: joblib
